pypots/__init__.py
pypots/base.py
pypots/version.py
pypots/anomaly_detection/__init__.py
pypots/anomaly_detection/base.py
pypots/anomaly_detection/autoformer/__init__.py
pypots/anomaly_detection/autoformer/model.py
pypots/anomaly_detection/crossformer/__init__.py
pypots/anomaly_detection/crossformer/model.py
pypots/anomaly_detection/dlinear/__init__.py
pypots/anomaly_detection/dlinear/model.py
pypots/anomaly_detection/etsformer/__init__.py
pypots/anomaly_detection/etsformer/model.py
pypots/anomaly_detection/fedformer/__init__.py
pypots/anomaly_detection/fedformer/model.py
pypots/anomaly_detection/film/__init__.py
pypots/anomaly_detection/film/model.py
pypots/anomaly_detection/imputeformer/__init__.py
pypots/anomaly_detection/imputeformer/model.py
pypots/anomaly_detection/informer/__init__.py
pypots/anomaly_detection/informer/model.py
pypots/anomaly_detection/itransformer/__init__.py
pypots/anomaly_detection/itransformer/model.py
pypots/anomaly_detection/nonstationary_transformer/__init__.py
pypots/anomaly_detection/nonstationary_transformer/model.py
pypots/anomaly_detection/patchtst/__init__.py
pypots/anomaly_detection/patchtst/model.py
pypots/anomaly_detection/pyraformer/__init__.py
pypots/anomaly_detection/pyraformer/model.py
pypots/anomaly_detection/reformer/__init__.py
pypots/anomaly_detection/reformer/model.py
pypots/anomaly_detection/saits/__init__.py
pypots/anomaly_detection/saits/model.py
pypots/anomaly_detection/scinet/__init__.py
pypots/anomaly_detection/scinet/model.py
pypots/anomaly_detection/segrnn/__init__.py
pypots/anomaly_detection/segrnn/model.py
pypots/anomaly_detection/tefn/__init__.py
pypots/anomaly_detection/tefn/model.py
pypots/anomaly_detection/timemixer/__init__.py
pypots/anomaly_detection/timemixer/model.py
pypots/anomaly_detection/timemixerpp/__init__.py
pypots/anomaly_detection/timemixerpp/model.py
pypots/anomaly_detection/timesnet/__init__.py
pypots/anomaly_detection/timesnet/model.py
pypots/anomaly_detection/transformer/__init__.py
pypots-1.1.dist-info/licenses/LICENSE
pypots-1.1.dist-info/METADATA
pypots-1.1.dist-info/WHEEL
pypots-1.1.dist-info/entry_points.txt
pypots-1.1.dist-info/top_level.txt
pypots-1.1.dist-info/RECORD
