Metadata-Version: 2.4
Name: pypots
Version: 1.1
Summary: A Python Toolbox for Machine Learning on Partially-Observed Time Series
Author-email: Wenjie Du <wenjay.du@gmail.com>
License: Copyright (c) 2023-present, Wenjie Du
Project-URL: Source, https://github.com/WenjieDu/PyPOTS
Project-URL: Homepage, https://pypots.com
Project-URL: Documentation, https://docs.pypots.com
Project-URL: Bug Tracker, https://github.com/WenjieDu/PyPOTS/issues
Project-URL: Download, https://github.com/WenjieDu/PyPOTS/archive/main.zip
Keywords: data science,data mining,neural networks,machine learning,deep learning,artificial intelligence,time-series analysis,time series,imputation,interpolation,classification,clustering,forecasting,partially observed,irregular sampled,partially-observed time series,incomplete time series,missing data,missing values
Classifier: Development Status :: 5 - Production/Stable
Classifier: Intended Audience :: Developers
Classifier: Intended Audience :: Education
Classifier: Intended Audience :: Science/Research
Classifier: Intended Audience :: Healthcare Industry
Classifier: License :: OSI Approved :: BSD License
Classifier: Operating System :: OS Independent
Classifier: Programming Language :: Python :: 3
Classifier: Programming Language :: Python :: 3.8
Classifier: Programming Language :: Python :: 3.9
Classifier: Programming Language :: Python :: 3.10
Classifier: Programming Language :: Python :: 3.11
Classifier: Topic :: Scientific/Engineering :: Artificial Intelligence
Classifier: Topic :: Software Development :: Libraries :: Application Frameworks
Requires-Python: >=3.8
License-File: LICENSE
Requires-Dist: h5py
Requires-Dist: numpy
Requires-Dist: scipy
Requires-Dist: sympy
Requires-Dist: einops
Requires-Dist: pandas
Requires-Dist: seaborn
Requires-Dist: matplotlib
Requires-Dist: tensorboard
Requires-Dist: scikit-learn
Requires-Dist: transformers
Requires-Dist: torch>=1.10.0
Requires-Dist: tsdb>=0.7.1
Requires-Dist: pygrinder>=0.7
Requires-Dist: benchpots>=0.4
Requires-Dist: ai4ts
Provides-Extra: dev
Requires-Dist: pypots>=1.0; extra == "dev"
Requires-Dist: build; extra == "dev"
Requires-Dist: torch-sparse; extra == "dev"
Requires-Dist: torch-scatter; extra == "dev"
Requires-Dist: torch-geometric; extra == "dev"
Requires-Dist: sentencepiece; extra == "dev"
Requires-Dist: pre-commit; extra == "dev"
Requires-Dist: jupyterlab; extra == "dev"
Requires-Dist: black; extra == "dev"
Requires-Dist: flake8; extra == "dev"
Requires-Dist: flake8-pyproject; extra == "dev"
Requires-Dist: coveralls; extra == "dev"
Requires-Dist: pytest-cov; extra == "dev"
Requires-Dist: pytest-xdist; extra == "dev"
Requires-Dist: furo; extra == "dev"
Requires-Dist: sphinx; extra == "dev"
Requires-Dist: sphinxcontrib-bibtex; extra == "dev"
Requires-Dist: sphinxcontrib-gtagjs; extra == "dev"
Requires-Dist: sphinx-autodoc-typehints; extra == "dev"
Dynamic: license-file
